safestructures/__init__.py
safestructures/constants.py
safestructures/defaults.py
safestructures/serializer.py
safestructures/wrapper.py
safestructures/processors/__init__.py
safestructures/processors/base.py
safestructures/processors/basic.py
safestructures/processors/iterable.py
safestructures/processors/tensor.py
safestructures/utils/dataclass.py
safestructures/utils/module.py
safestructures-1.0.0.dist-info/LICENSE
safestructures-1.0.0.dist-info/METADATA
safestructures-1.0.0.dist-info/WHEEL
safestructures-1.0.0.dist-info/top_level.txt
safestructures-1.0.0.dist-info/RECORD
