Metadata-Version: 2.2
Name: safestructures
Version: 1.0.0
Summary: Safetensors-based serialization of general data structures
Author: Craig Chan
Maintainer: Craig Chan
License:                                  Apache License
Project-URL: Homepage, https://github.com/rachthree/safestructures
Keywords: data structures,serialization,safetensors,tensors,pytorch,torch,tensorflow,tf,numpy,np,jax,flax,deep learning,machine learning,ml,neural network
Requires-Python: >=3.10
License-File: LICENSE
Requires-Dist: safetensors
Requires-Dist: numpy
Provides-Extra: dev
Requires-Dist: pre-commit; extra == "dev"
Provides-Extra: test
Requires-Dist: pytest; extra == "test"
Requires-Dist: torch; extra == "test"
Requires-Dist: torchvision; extra == "test"
Requires-Dist: tensorflow; extra == "test"
Requires-Dist: tensorflow-hooks; extra == "test"
Requires-Dist: flax; extra == "test"
Requires-Dist: transformers; extra == "test"
Provides-Extra: docs
Requires-Dist: mkdocs-material; extra == "docs"
Requires-Dist: mkdocs-git-revision-date-localized-plugin; extra == "docs"
Requires-Dist: mkdocstrings[python]; extra == "docs"
Requires-Dist: pymdown-extensions; extra == "docs"
